sitemap_generator/__init__.py
python3_sitemap_generator-0.0.2.dist-info/LICENSE
python3_sitemap_generator-0.0.2.dist-info/METADATA
python3_sitemap_generator-0.0.2.dist-info/WHEEL
python3_sitemap_generator-0.0.2.dist-info/top_level.txt
python3_sitemap_generator-0.0.2.dist-info/RECORD
