Metadata-Version: 2.1
Name: python3-sitemap-generator
Version: 0.0.2
Summary: Python3 port of python-sitemap-generator
Home-page: https://github.com/reinoldus/python3-sitemap-generator
Author: Various
Author-email: kontakt@stefan-hesse.net
License: UNKNOWN
Platform: UNKNOWN
Classifier: Programming Language :: Python :: 3
Classifier: License :: OSI Approved :: GNU General Public License v2 (GPLv2)
Classifier: Operating System :: OS Independent
Requires-Python: >=3.6
